ecoserver/__init__.py
ecoserver/api_client.py
ecoserver/configuration.py
ecoserver/rest.py
ecoserver/api/__init__.py
ecoserver/api/admin_api.py
ecoserver/api/chat_api.py
ecoserver/api/command_api.py
ecoserver/api/data_export_api.py
ecoserver/api/election_api.py
ecoserver/api/law_api.py
ecoserver/api/log_api.py
ecoserver/api/map_api.py
ecoserver/api/plugins_api.py
ecoserver/api/profiling_results_api.py
ecoserver/api/root_api.py
ecoserver/api/stats_api.py
ecoserver/api/users_api.py
ecoserver/api/world_layer_api.py
ecoserver/models/__init__.py
ecoserver/models/eco_gameplay_civics_elections_choice_results.py
ecoserver/models/eco_shared_items_proposable_state.py
ecoserver/models/eco_shared_localization_loc_string.py
ecoserver/models/eco_shared_math_ray.py
ecoserver/models/eco_shared_math_vector2i.py
ecoserver/models/eco_shared_math_vector3i.py
ecoserver/models/eco_shared_networking_server_info.py
ecoserver/models/eco_shared_networking_skill_specialization_setting.py
ecoserver/models/eco_shared_states_server_category.py
ecoserver/models/eco_stats_graph.py
ecoserver/models/eco_stats_key.py
ecoserver/models/eco_stats_named_graph.py
ecoserver/models/eco_stats_stat_category.py
ecoserver/models/eco_stats_stat_info.py
ecoserver/models/eco_web_server_data_transfer_objects_chat_message_dto.py
ecoserver/models/eco_web_server_data_transfer_objects_civic_action_dto.py
ecoserver/models/eco_web_server_data_transfer_objects_command_result_dto.py
ecoserver/models/eco_web_server_data_transfer_objects_district_dto.py
ecoserver/models/eco_web_server_data_transfer_objects_district_map_dto.py
ecoserver/models/eco_web_server_data_transfer_objects_elected_title_dto.py
ecoserver/models/eco_web_server_data_transfer_objects_election_choice_dto.py
ecoserver/models/eco_web_server_data_transfer_objects_election_comment_dto.py
ecoserver/models/eco_web_server_data_transfer_objects_election_dto.py
ecoserver/models/eco_web_server_data_transfer_objects_election_process_dto.py
ecoserver-1.0.0.dist-info/METADATA
ecoserver-1.0.0.dist-info/WHEEL
ecoserver-1.0.0.dist-info/top_level.txt
ecoserver-1.0.0.dist-info/RECORD
